flask_jsonapi/__init__.py
flask_jsonapi/api.py
flask_jsonapi/decorators.py
flask_jsonapi/descriptors.py
flask_jsonapi/exceptions.py
flask_jsonapi/filters_schema.py
flask_jsonapi/query_string.py
flask_jsonapi/resource_repository_views.py
flask_jsonapi/resources.py
flask_jsonapi/response.py
flask_jsonapi/permissions/__init__.py
flask_jsonapi/permissions/actions.py
flask_jsonapi/permissions/checkers.py
flask_jsonapi/permissions/views.py
flask_jsonapi/resource_repositories/__init__.py
flask_jsonapi/resource_repositories/repositories.py
flask_jsonapi/resource_repositories/sqlalchemy_repositories.py
flask_jsonapi/utils/__init__.py
flask_jsonapi/utils/common.py
flask_jsonapi/utils/sqlalchemy_django_query.py
tests/permissions/__init__.py
tests/permissions/test_checkers.py
tests/permissions/test_views.py
tests/sqlalchemy_repository/__init__.py
tests/sqlalchemy_repository/conftest.py
tests/sqlalchemy_repository/test_sqlalchemy_repository_basic.py
tests/sqlalchemy_repository/test_sqlalchemy_repository_integration.py
tests/sqlalchemy_repository/test_sqlalchemy_repository_pagination.py
tests/sqlalchemy_repository/test_sqlalchemy_repository_sort.py
tests/sqlalchemy_repository/filter_backend/__init__.py
tests/sqlalchemy_repository/filter_backend/test_sqlachemy_repository_many_to_many_direct_association_filters.py
tests/sqlalchemy_repository/filter_backend/test_sqlachemy_repository_many_to_many_secondary_filters.py
tests/sqlalchemy_repository/filter_backend/test_sqlachemy_repository_one_to_many_relationship_filters.py
tests/sqlalchemy_repository/filter_backend/test_sqlachemy_repository_one_to_one_relationship_filters.py
tests/sqlalchemy_repository/filter_backend/test_sqlalchemy_repository_filter_backend.py
tests/sqlalchemy_repository/utils/__init__.py
tests/sqlalchemy_repository/utils/test_sqlalchemy_django_query.py
flask_jsonapi-1.3.0.dist-info/AUTHORS
flask_jsonapi-1.3.0.dist-info/LICENSE
flask_jsonapi-1.3.0.dist-info/METADATA
flask_jsonapi-1.3.0.dist-info/WHEEL
flask_jsonapi-1.3.0.dist-info/top_level.txt
flask_jsonapi-1.3.0.dist-info/RECORD
