Metadata-Version: 2.1
Name: flask-jsonapi
Version: 1.3.0
Summary: JSONAPI 1.0 implementation for Flask.
Home-page: https://github.com/socialwifi/flask-jsonapi
Author: Social WiFi
Author-email: it@socialwifi.com
License: BSD
Platform: UNKNOWN
Classifier: Development Status :: 5 - Production/Stable
Classifier: Environment :: Console
Classifier: Intended Audience :: Developers
Classifier: License :: OSI Approved :: BSD License
Classifier: Operating System :: OS Independent
Classifier: Programming Language :: Python
Classifier: Programming Language :: Python :: 3
Classifier: Programming Language :: Python :: 3.7
Classifier: Programming Language :: Python :: 3.8
Classifier: Programming Language :: Python :: 3.9
Requires-Dist: Flask
Requires-Dist: marshmallow (>=3.0.0)
Requires-Dist: marshmallow-jsonapi
Provides-Extra: sqlalchemy
Requires-Dist: sqlalchemy ; extra == 'sqlalchemy'
Requires-Dist: sqlalchemy-utils ; extra == 'sqlalchemy'
